codebase_ai_prompt_generator-0.1.2.dist-info/licenses/LICENSE
codebase_prompt_gen/__init__.py
codebase_prompt_gen/core.py
codebase_prompt_gen/cli/__init__.py
codebase_prompt_gen/cli/main.py
codebase_ai_prompt_generator-0.1.2.dist-info/METADATA
codebase_ai_prompt_generator-0.1.2.dist-info/WHEEL
codebase_ai_prompt_generator-0.1.2.dist-info/entry_points.txt
codebase_ai_prompt_generator-0.1.2.dist-info/top_level.txt
codebase_ai_prompt_generator-0.1.2.dist-info/RECORD
