Metadata-Version: 2.4
Name: codebase-ai-prompt-generator
Version: 0.1.2
Summary: Generate AI prompts from Git repositories with file tree structures and content
Author-email: Yiping Deng <yiping.deng.98@gmail.com>
License: MIT
Project-URL: Homepage, https://github.com/DengYiping/codebase-ai-prompt-generator
Project-URL: Bug Tracker, https://github.com/DengYiping/codebase-ai-prompt-generator/issues
Project-URL: Documentation, https://github.com/DengYiping/codebase-ai-prompt-generator#readme
Keywords: ai,prompt,git,code,repository,cursor,ai-assistant
Classifier: Development Status :: 4 - Beta
Classifier: Intended Audience :: Developers
Classifier: Topic :: Software Development :: Libraries :: Python Modules
Classifier: License :: OSI Approved :: MIT License
Classifier: Programming Language :: Python :: 3
Classifier: Programming Language :: Python :: 3.10
Classifier: Programming Language :: Python :: 3.11
Classifier: Programming Language :: Python :: 3.12
Classifier: Programming Language :: Python :: 3.13
Requires-Python: >=3.10
License-File: LICENSE
Requires-Dist: gitignore-parser>=0.1.11
Dynamic: license-file
